{"name":"build-javascript","namedChunkGroups":{"polyfill":{"name":"polyfill","assets":[{"name":"webpack-runtime-649fbc99911de7d74dee.js","size":5006},{"name":"polyfill-4718f0fec20e0d09d7f5.js","size":85862}],"filteredAssets":0,"assetsSize":90868,"filteredAuxiliaryAssets":2,"auxiliaryAssetsSize":228012},"app":{"name":"app","assets":[{"name":"webpack-runtime-649fbc99911de7d74dee.js","size":5006},{"name":"framework-6bdc9aaa9caa3de6408b.js","size":129775},{"name":"app-38f8950f994ba89f7700.js","size":153164}],"filteredAssets":0,"assetsSize":287945,"filteredAuxiliaryAssets":3,"auxiliaryAssetsSize":1066961},"component---src-pages-404-js":{"name":"component---src-pages-404-js","assets":[{"name":"component---src-pages-404-js-55ebbc4a508168189bb7.js","size":261}],"filteredAssets":0,"assetsSize":261,"filteredAuxiliaryAssets":1,"auxiliaryAssetsSize":304},"component---src-pages-index-jsx":{"name":"component---src-pages-index-jsx","assets":[{"name":"styles.5d9841bc51a4d8a4450d.css","size":50502},{"name":"component---src-pages-index-jsx-a9327927a64a57a27a0f.js","size":17354}],"filteredAssets":0,"assetsSize":67856,"filteredAuxiliaryAssets":1,"auxiliaryAssetsSize":54850},"component---src-pages-login-jsx":{"name":"component---src-pages-login-jsx","assets":[{"name":"styles.5d9841bc51a4d8a4450d.css","size":50502},{"name":"component---src-pages-login-jsx-14b66aedff3b64724ba5.js","size":10942}],"filteredAssets":0,"assetsSize":61444,"filteredAuxiliaryAssets":1,"auxiliaryAssetsSize":37255},"component---src-pages-login-or-signup-jsx":{"name":"component---src-pages-login-or-signup-jsx","assets":[{"name":"styles.5d9841bc51a4d8a4450d.css","size":50502},{"name":"component---src-pages-login-or-signup-jsx-f303893febe55be0182f.js","size":16232}],"filteredAssets":0,"assetsSize":66734,"filteredAuxiliaryAssets":1,"auxiliaryAssetsSize":44887}},"assetsByChunkName":{"polyfill":["webpack-runtime-649fbc99911de7d74dee.js","polyfill-4718f0fec20e0d09d7f5.js"],"app":["webpack-runtime-649fbc99911de7d74dee.js","framework-6bdc9aaa9caa3de6408b.js","app-38f8950f994ba89f7700.js"],"component---src-pages-404-js":["component---src-pages-404-js-55ebbc4a508168189bb7.js"],"component---src-pages-index-jsx":["styles.5d9841bc51a4d8a4450d.css","component---src-pages-index-jsx-a9327927a64a57a27a0f.js"],"component---src-pages-login-jsx":["styles.5d9841bc51a4d8a4450d.css","component---src-pages-login-jsx-14b66aedff3b64724ba5.js"],"component---src-pages-login-or-signup-jsx":["styles.5d9841bc51a4d8a4450d.css","component---src-pages-login-or-signup-jsx-f303893febe55be0182f.js"]},"childAssetsByChunkName":{}}